CHANGES.rst
CONTRIBUTORS.rst
MANIFEST.in
README.rst
setup.cfg
setup.py
docs/LICENSE.GPL
docs/LICENSE.rst
docs/forContent.png
docs/index.rst
src/collective/__init__.py
src/collective.getfeed.egg-info/PKG-INFO
src/collective.getfeed.egg-info/SOURCES.txt
src/collective.getfeed.egg-info/dependency_links.txt
src/collective.getfeed.egg-info/entry_points.txt
src/collective.getfeed.egg-info/namespace_packages.txt
src/collective.getfeed.egg-info/not-zip-safe
src/collective.getfeed.egg-info/requires.txt
src/collective.getfeed.egg-info/top_level.txt
src/collective/getfeed/__init__.py
src/collective/getfeed/configure.zcml
src/collective/getfeed/content.py
src/collective/getfeed/interfaces.py
src/collective/getfeed/setuphandlers.py
src/collective/getfeed/testing.py
src/collective/getfeed/upgrades.py
src/collective/getfeed/upgrades.zcml
src/collective/getfeed/browser/__init__.py
src/collective/getfeed/browser/configure.zcml
src/collective/getfeed/browser/feed.pt
src/collective/getfeed/browser/feed_item.pt
src/collective/getfeed/browser/getfeeds.py
src/collective/getfeed/browser/overrides/.gitkeep
src/collective/getfeed/browser/static/.gitkeep
src/collective/getfeed/browser/static/feed.css
src/collective/getfeed/browser/static/feed.svg
src/collective/getfeed/locales/collective.getfeed.pot
src/collective/getfeed/locales/update.sh
src/collective/getfeed/locales/de/LC_MESSAGES/plone.po
src/collective/getfeed/profiles/default/actions.xml
src/collective/getfeed/profiles/default/browserlayer.xml
src/collective/getfeed/profiles/default/cssregistry.xml
src/collective/getfeed/profiles/default/metadata.xml
src/collective/getfeed/profiles/default/types.xml
src/collective/getfeed/profiles/default/types/Feed.xml
src/collective/getfeed/profiles/default/types/Feed_Item.xml
src/collective/getfeed/profiles/uninstall/browserlayer.xml
src/collective/getfeed/tests/__init__.py
src/collective/getfeed/tests/test_feed.py
src/collective/getfeed/tests/test_feeditem.py
src/collective/getfeed/tests/test_robot.py
src/collective/getfeed/tests/test_setup.py
src/collective/getfeed/tests/test_views.py
src/collective/getfeed/tests/examples/feed1.rss
src/collective/getfeed/tests/examples/feed2.rss
src/collective/getfeed/tests/robot/test_example.robot