Metadata-Version: 2.1
Name: collective.getfeed
Version: 1.0.0a6
Summary: UNKNOWN
Home-page: https://github.com/collective/collective.getfeed
Author: forContent
Author-email: suporte@forcontent.com.br
License: GPL version 2
Keywords: Python Plone
Platform: UNKNOWN
Classifier: Environment :: Web Environment
Classifier: Framework :: Plone
Classifier: Framework :: Plone :: 5.1
Classifier: Programming Language :: Python
Classifier: Programming Language :: Python :: 2.7
Classifier: Operating System :: OS Independent
Classifier: License :: OSI Approved :: GNU General Public License v2 (GPLv2)
Provides-Extra: test
